farmgbm12/GeometricBrownian.py
farmgbm12/__init__.py
farmgbm12/gbm_cli.py
farmgbm12/run_simulation.py
farmgbm12-0.2.0.dist-info/METADATA
farmgbm12-0.2.0.dist-info/WHEEL
farmgbm12-0.2.0.dist-info/RECORD
