Metadata-Version: 2.1
Name: farmgbm12
Version: 0.2.0
Summary: Package Simulates Geometric Brownian Motion
Author: Farmer122
Author-email: 94114999+Farmer122@users.noreply.github.com
Requires-Python: >=3.12,<4.0
Classifier: Programming Language :: Python :: 3
Classifier: Programming Language :: Python :: 3.12
Classifier: Programming Language :: Python :: 3.13
